pyqt_reactivity/__init__.py
pyqt_reactivity/base.py
pyqt_reactivity/binding.py
pyqt_reactivity/computed.py
pyqt_reactivity/lifecycle/__init__.py
pyqt_reactivity/lifecycle/stack.py
pyqt_reactivity/lifecycle/undo.py
pyqt_reactivity/lifecycle/viewmodel.py
pyqt_reactivity/lifecycle/worker.py
pyqt_reactivity/ref.py
pyqt_reactivity/utils.py
pyqt_reactivity/watch.py
pyqt_reactivity-0.3.0.dist-info/LICENSE
pyqt_reactivity-0.3.0.dist-info/METADATA
pyqt_reactivity-0.3.0.dist-info/WHEEL
pyqt_reactivity-0.3.0.dist-info/entry_points.txt
pyqt_reactivity-0.3.0.dist-info/RECORD
