Metadata-Version: 2.1
Name: pyqt_reactivity
Version: 0.3.0
Summary: Reactivity library for PyQT
Home-page: https://github.com/indrarudianto/pyqt-reactivity
License: MIT
Author: Indra Rudianto
Author-email: indrarudianto.official@gmail.com
Requires-Python: >=3.10
Classifier: License :: OSI Approved :: MIT License
Classifier: Programming Language :: Python :: 3
Classifier: Programming Language :: Python :: 3.10
Classifier: Programming Language :: Python :: 3.11
Classifier: Programming Language :: Python :: 3.12
Classifier: Programming Language :: Python :: 3.13
Requires-Dist: qtpy (>=2.4.1,<3.0.0)
Project-URL: Repository, https://github.com/indrarudianto/pyqt-reactivity
